lectricus.py
lectricus/__init__.py
lectricus/binary_classification.py
lectricus/binary_search.py
lectricus/command_line.py
lectricus/export_results.py
lectricus/electron_exploits/__init__.py
lectricus/electron_exploits/base.py
lectricus/electron_exploits/inspect.py
lectricus/electron_exploits/nwjs.py
lectricus/electron_exploits/run_as_node.py
lectricus-1.0.1.dist-info/METADATA
lectricus-1.0.1.dist-info/WHEEL
lectricus-1.0.1.dist-info/entry_points.txt
lectricus-1.0.1.dist-info/top_level.txt
lectricus-1.0.1.dist-info/RECORD
