Metadata-Version: 2.1
Name: lectricus
Version: 1.0.1
Summary: Electron and NWJS Vulnerability Detection Utility
Home-page: https://github.com/ripeda/lectricus
Author: RIPEDA Consulting
Author-email: info@ripeda.com
License: 3-clause BSD License
Classifier: Programming Language :: Python :: 3
Classifier: License :: OSI Approved :: BSD License
Classifier: Operating System :: MacOS :: MacOS X
Classifier: Operating System :: Microsoft :: Windows
Classifier: Operating System :: POSIX :: Linux
Classifier: Development Status :: 5 - Production/Stable
Requires-Python: >=3.6
Requires-Dist: electron-search >=1.3.1
Requires-Dist: electron-fuses >=1.2.0
Requires-Dist: websocket-client >=1.7.0
Requires-Dist: packaging >=23.0
